odious/__init__.py
odious/config.py
odious/matchup.py
odious-0.0.4.dist-info/LICENSE
odious-0.0.4.dist-info/METADATA
odious-0.0.4.dist-info/WHEEL
odious-0.0.4.dist-info/top_level.txt
odious-0.0.4.dist-info/RECORD
