Metadata-Version: 2.1
Name: odious
Version: 0.0.4
Summary: Optimizer comparisons
Home-page: https://github.com/microprediction/odious
Author: microprediction
Author-email: pcotton@intechinvestments.com
License: MIT
Platform: UNKNOWN
Classifier: License :: OSI Approved :: MIT License
Classifier: Programming Language :: Python :: 3
Classifier: Programming Language :: Python :: 3.7
Requires-Dist: wheel
Requires-Dist: pathlib
Requires-Dist: numpy (>=1.16.5)
Requires-Dist: timemachines
Requires-Dist: pytest
Requires-Dist: microprediction
